{
	"name": "Ejecucion Completa",
	"properties": {
		"activities": [
			{
				"name": "LFS_terceros_SAP",
				"type": "ExecutePipeline",
				"dependsOn": [],
				"userProperties": [],
				"typeProperties": {
					"pipeline": {
						"referenceName": "SAP_LFS_Terceros",
						"type": "PipelineReference"
					},
					"waitOnCompletion": true
				}
			},
			{
				"name": "Primus_LFS_Customer",
				"type": "ExecutePipeline",
				"dependsOn": [
					{
						"activity": "LFS_terceros_SAP",
						"dependencyConditions": [
							"Succeeded"
						]
					}
				],
				"userProperties": [],
				"typeProperties": {
					"pipeline": {
						"referenceName": "Primus_Customer",
						"type": "PipelineReference"
					},
					"waitOnCompletion": true
				}
			},
			{
				"name": "Primus_LFS_Vendor",
				"type": "ExecutePipeline",
				"dependsOn": [
					{
						"activity": "Primus_LFS_Customer",
						"dependencyConditions": [
							"Succeeded"
						]
					}
				],
				"userProperties": [],
				"typeProperties": {
					"pipeline": {
						"referenceName": "Primus_Vendor",
						"type": "PipelineReference"
					},
					"waitOnCompletion": true
				}
			},
			{
				"name": "Shipment",
				"type": "ExecutePipeline",
				"dependsOn": [
					{
						"activity": "Primus_LFS_Vendor",
						"dependencyConditions": [
							"Succeeded"
						]
					}
				],
				"userProperties": [],
				"typeProperties": {
					"pipeline": {
						"referenceName": "Shipment",
						"type": "PipelineReference"
					},
					"waitOnCompletion": true
				}
			},
			{
				"name": "Invoice",
				"type": "ExecutePipeline",
				"dependsOn": [
					{
						"activity": "Shipment",
						"dependencyConditions": [
							"Succeeded"
						]
					}
				],
				"userProperties": [],
				"typeProperties": {
					"pipeline": {
						"referenceName": "Invoice",
						"type": "PipelineReference"
					},
					"waitOnCompletion": true
				}
			},
			{
				"name": "Quote",
				"type": "ExecutePipeline",
				"dependsOn": [
					{
						"activity": "Invoice",
						"dependencyConditions": [
							"Succeeded"
						]
					}
				],
				"userProperties": [],
				"typeProperties": {
					"pipeline": {
						"referenceName": "Quote",
						"type": "PipelineReference"
					},
					"waitOnCompletion": true
				}
			},
			{
				"name": "SAP_LFS_Factura",
				"type": "ExecutePipeline",
				"dependsOn": [
					{
						"activity": "Quote",
						"dependencyConditions": [
							"Succeeded"
						]
					}
				],
				"userProperties": [],
				"typeProperties": {
					"pipeline": {
						"referenceName": "SAP_LFS_Factura",
						"type": "PipelineReference"
					},
					"waitOnCompletion": true
				}
			}
		],
		"folder": {
			"name": "Azure"
		},
		"annotations": []
	},
	"type": "Microsoft.DataFactory/factories/pipelines"
}